crawler/__init__.py
crawler/main.py
crawler/scrapy.cfg
crawler/hls_downloader/__init__.py
crawler/hls_downloader/items.py
crawler/hls_downloader/middlewares.py
crawler/hls_downloader/pipelines.py
crawler/hls_downloader/settings.py
crawler/hls_downloader/spiders/__init__.py
crawler/hls_downloader/spiders/test-spider.py
crawler/hls_downloader/spiders/video_spider.py
crawler/hls_downloader/utils/__init__.py
crawler/hls_downloader/utils/ffmpeg
crawler/hls_downloader/utils/m3u8_parser.py
crawler/hls_downloader/utils/merge_ts.py
scrapy_hls-0.1.dist-info/METADATA
scrapy_hls-0.1.dist-info/WHEEL
scrapy_hls-0.1.dist-info/entry_points.txt
scrapy_hls-0.1.dist-info/top_level.txt
scrapy_hls-0.1.dist-info/RECORD
